restoreio/__init__.py
restoreio/__main__.py
restoreio/__version__.py
restoreio/_file_utilities/__init__.py
restoreio/_file_utilities/file_utilities.py
restoreio/_geography/__init__.py
restoreio/_geography/_find_alpha_shapes.py
restoreio/_geography/create_mask_info.py
restoreio/_geography/detect_land_ocean.py
restoreio/_geography/locate_missing_data.py
restoreio/_inpaint/__init__.py
restoreio/_inpaint/_cast_types.py
restoreio/_inpaint/_image.py
restoreio/_inpaint/_plot_image.py
restoreio/_inpaint/inpaint.py
restoreio/_input_output/__init__.py
restoreio/_input_output/get_datetime_info.py
restoreio/_input_output/license.py
restoreio/_input_output/load_dataset.py
restoreio/_input_output/load_variables.py
restoreio/_input_output/writer.py
restoreio/_parser/__init__.py
restoreio/_parser/examples.py
restoreio/_parser/formatter.py
restoreio/_parser/parse_arguments.py
restoreio/_plots/__init__.py
restoreio/_plots/_display_utilities.py
restoreio/_plots/_draw_map.py
restoreio/_plots/_plot_grid.py
restoreio/_plots/_plot_quiver.py
restoreio/_plots/_plot_streamlines.py
restoreio/_plots/_plot_utilities.py
restoreio/_plots/_plot_velocities.py
restoreio/_plots/plot_results.py
restoreio/_plots_uq/__init__.py
restoreio/_plots_uq/_refine_mask.py
restoreio/_plots_uq/_shifted_colormap.py
restoreio/_plots_uq/plot_auto_correlation.py
restoreio/_plots_uq/plot_convergence.py
restoreio/_plots_uq/plot_cor_cov.py
restoreio/_plots_uq/plot_ensembles_stat.py
restoreio/_plots_uq/plot_kl_transform.py
restoreio/_plots_uq/plot_outliers.py
restoreio/_plots_uq/plot_rbf_kernel.py
restoreio/_plots_uq/plot_valid_vector_ensembles_stat.py
restoreio/_restore/__init__.py
restoreio/_restore/_make_array_masked.py
restoreio/_restore/refine_grid.py
restoreio/_restore/restore_generated_ensembles.py
restoreio/_restore/restore_main_ensemble.py
restoreio/_scripts/__init__.py
restoreio/_scripts/examples.py
restoreio/_scripts/scan.py
restoreio/_server_utils/__init__.py
restoreio/_server_utils/globals.py
restoreio-0.10.1.dist-info/AUTHORS.txt
restoreio-0.10.1.dist-info/LICENSE.txt
restoreio-0.10.1.dist-info/METADATA
restoreio-0.10.1.dist-info/WHEEL
restoreio-0.10.1.dist-info/entry_points.txt
restoreio-0.10.1.dist-info/top_level.txt
restoreio-0.10.1.dist-info/RECORD
