Metadata-Version: 2.1
Name: restoreio
Version: 0.10.1
Summary: Reconstruct incomplete oceanographic dataset
Home-page: https://github.com/ameli/restoreio
Download-URL: https://github.com/ameli/restoreio/archive/main.zip
Author: Siavash Ameli
Author-email: sameli@berkeley.edu
Project-URL: Documentation, https://github.com/ameli/restoreio/blob/main/README.rst
Project-URL: Source, https://github.com/ameli/restoreio
Project-URL: Tracker, https://github.com/ameli/restoreio/issues
Keywords: reconstruct-data oceanographic-data hf-radar
Platform: Linux
Platform: OSX
Platform: Windows
Classifier: Programming Language :: Python
Classifier: Programming Language :: Python :: 3.9
Classifier: Programming Language :: Python :: 3.10
Classifier: Programming Language :: Python :: 3.11
Classifier: Programming Language :: Python :: 3.12
Classifier: Programming Language :: Python :: Implementation :: CPython
Classifier: License :: OSI Approved :: BSD License
Classifier: Operating System :: POSIX :: Linux
Classifier: Operating System :: Microsoft :: Windows
Classifier: Operating System :: MacOS
Classifier: Natural Language :: English
Classifier: Intended Audience :: Science/Research
Classifier: Intended Audience :: Developers
Classifier: Topic :: Software Development
Classifier: Topic :: Software Development :: Libraries :: Python Modules
Classifier: Topic :: Scientific/Engineering
Requires-Python: >=3.9
License-File: LICENSE.txt
License-File: AUTHORS.txt
Requires-Dist: numpy
Requires-Dist: scipy
Requires-Dist: pyncml
Requires-Dist: netCDF4
Requires-Dist: opencv-python-headless
Requires-Dist: shapely
Requires-Dist: pyDOE
Requires-Dist: matplotlib
Requires-Dist: proj
Requires-Dist: pyproj
Requires-Dist: geos
Requires-Dist: basemap
Requires-Dist: basemap-data
Requires-Dist: basemap-data-hires
Provides-Extra: docs
Requires-Dist: sphinx ; extra == 'docs'
Requires-Dist: sphinx-math-dollar ; extra == 'docs'
Requires-Dist: sphinx-toggleprompt <0.4 ; extra == 'docs'
Requires-Dist: pydata-sphinx-theme ==0.9.0 ; extra == 'docs'
Requires-Dist: graphviz ; extra == 'docs'
Requires-Dist: sphinx-automodapi ; extra == 'docs'
Requires-Dist: numpydoc ; extra == 'docs'
Requires-Dist: nbsphinx ; extra == 'docs'
Requires-Dist: sphinx-design ; extra == 'docs'
Requires-Dist: sphinx-multitoc-numbering ; extra == 'docs'
Requires-Dist: sphinx-prompt ; extra == 'docs'
Requires-Dist: sphinx-copybutton ; extra == 'docs'
Requires-Dist: sphinx-gallery ; extra == 'docs'
Requires-Dist: sphinxext-opengraph ; extra == 'docs'
Requires-Dist: jinja2 ==3.1.2 ; extra == 'docs'
Requires-Dist: sphinx-argparse ; extra == 'docs'
Requires-Dist: scipy ; extra == 'docs'
Provides-Extra: test
Requires-Dist: pytest-cov ; extra == 'test'
Requires-Dist: codecov ; extra == 'test'
